madlab
