Metadata-Version: 2.1
Name: madlab
Version: 0.0.4
Summary: madlab client module
Home-page: UNKNOWN
Author: Sebastien Campion
Author-email: sebastien.campion@inria.fr
License: AGPL
Platform: UNKNOWN
Classifier: Programming Language :: Python
Classifier: Development Status :: 1 - Planning
Classifier: License :: OSI Approved
Classifier: Natural Language :: French
Classifier: Operating System :: OS Independent
Classifier: Programming Language :: Python :: 3.6
Classifier: Topic :: Communications
